setup.cfg
setup.py
word2veckeras/__init__.py
word2veckeras/doc2veckeras.py
word2veckeras/scoreword2veckeras.py
word2veckeras/treebank.py
word2veckeras/word2veckeras.py
word2veckeras.egg-info/PKG-INFO
word2veckeras.egg-info/SOURCES.txt
word2veckeras.egg-info/dependency_links.txt
word2veckeras.egg-info/requires.txt
word2veckeras.egg-info/top_level.txt