Metadata-Version: 1.1
Name: word2veckeras
Version: 0.0.5.2
Summary: word2vec based on Kearas and gensim
Home-page: https://github.com/niitsuma/word2vec-keras-in-gensim
Author: Hirotaka Niitsuma
Author-email: hirotaka.niitsuma@gmail.com
License: GNU Affero General Public License, version 3 - http://www.gnu.org/licenses/agpl-3.0.html
Download-URL: https://github.com/niitsuma/word2vec-keras-in-gensim/archive/master.zip
Platform: UNKNOWN
